[
  {
    "title": "Serving These Areas:",
    "items": [
      {
        "link": "",
        "item": "Dayton"
      },
      {
        "link": "",
        "item": "Kettering"
      },
      {
        "link": "",
        "item": "Centerville"
      },
      {
        "link": "",
        "item": "Bellebrook"
      },
      {
        "link": "",
        "item": "Springboro"
      },
      {
        "link": "",
        "item": "Fairborn"
      },
      {
        "link": "",
        "item": "Miamisburg"
      },
      {
        "link": "",
        "item": "Beavercreak"
      },
      {
        "link": "",
        "item": "Green County"
      },
      {
        "link": "",
        "item": "Montgomery County"
      },
      {
        "link": "",
        "item": "Buttler County"
      },
      {
        "link": "",
        "item": "Warren County"
      }
    ]
  },
  {
    "title": "Our Training Packages",
    "items": [
      {
        "link": "/classes#PrivateLessons",
        "item": "Private Lessons"
      },
      {
        "link": "/classes#DogWalks",
        "item": "Dog Walking"
      },
      {
        "link": "/classes#GroupClasses",
        "item": "Group Classes"
      },
      {
        "link": "/classes#SniffWalks",
        "item": "Sniff Walk"
      },
      {
        "link": "/classes#StructureWalk",
        "item": "Structure Walk"
      },
      {
        "link": "/classes#ReactiveDog",
        "item": "Reactive Dog"
      },
      {
        "link": "/classes#GroupHike",
        "item": "Group Hike"
      },
      {
        "link": "/classes#CGCPrep",
        "item": "Canine Good Citizen"
      },
      {
        "link": "/classes#AKCStarPuppy",
        "item": "Star Puppy Group Classes"
      },
      {
        "link": "/classes#SportSamples",
        "item": "Dog Sports"
      },
      {
        "link": "/classes#ConfidenceBuilding",
        "item": "Confidence Building"
      }
    ]
  },
  {
    "title": "Popular Articles",
    "items": [
      {
        "link": "",
        "item": "Puppy Training Guide"
      },
      {
        "link": "",
        "item": "Firework Desensitation"
      },
      {
        "link": "",
        "item": "Teaching your dog to walk on a leash"
      }
    ]
  }
]
